py_aiovk/__init__.py
py_aiovk/callback.py
py_aiovk/events.py
py_aiovk/longpoll.py
py_aiovk/vk.py
py_aiovk/methods/__init__.py
py_aiovk/methods/account.py
py_aiovk/methods/appWidgets.py
py_aiovk/methods/apps.py
py_aiovk/methods/audio.py
py_aiovk/methods/auth.py
py_aiovk/methods/board.py
py_aiovk/methods/database.py
py_aiovk/methods/docs.py
py_aiovk/methods/donut.py
py_aiovk/methods/fave.py
py_aiovk/methods/friends.py
py_aiovk/methods/groups.py
py_aiovk/methods/likes.py
py_aiovk/methods/market.py
py_aiovk/methods/messages.py
py_aiovk/methods/newsfeed.py
py_aiovk/methods/notes.py
py_aiovk/methods/photos.py
py_aiovk/methods/podcasts.py
py_aiovk/methods/polls.py
py_aiovk/methods/search.py
py_aiovk/methods/status.py
py_aiovk/methods/storage.py
py_aiovk/methods/store.py
py_aiovk/methods/stories.py
py_aiovk/methods/users.py
py_aiovk/methods/utils.py
py_aiovk/methods/video.py
py_aiovk/methods/wall.py
py_aiovk/types/__init__.py
py_aiovk/types/messages.py
py_aiovk/types/params/__init__.py
py_aiovk/types/params/account.py
py_aiovk/types/params/appWidgets.py
py_aiovk/types/params/apps.py
py_aiovk/types/params/audio.py
py_aiovk/types/params/auth.py
py_aiovk/types/params/board.py
py_aiovk/types/params/database.py
py_aiovk/types/params/docs.py
py_aiovk/types/params/donut.py
py_aiovk/types/params/fave.py
py_aiovk/types/params/friends.py
py_aiovk/types/params/groups.py
py_aiovk/types/params/likes.py
py_aiovk/types/params/market.py
py_aiovk/types/params/messages.py
py_aiovk/types/params/newsfeed.py
py_aiovk/types/params/notes.py
py_aiovk/types/params/photos.py
py_aiovk/types/params/podcasts.py
py_aiovk/types/params/polls.py
py_aiovk/types/params/search.py
py_aiovk/types/params/status.py
py_aiovk/types/params/storage.py
py_aiovk/types/params/store.py
py_aiovk/types/params/stories.py
py_aiovk/types/params/users.py
py_aiovk/types/params/utils.py
py_aiovk/types/params/video.py
py_aiovk/types/params/wall.py
py_aiovk-0.0.3.dist-info/LICENSE
py_aiovk-0.0.3.dist-info/METADATA
py_aiovk-0.0.3.dist-info/WHEEL
py_aiovk-0.0.3.dist-info/top_level.txt
py_aiovk-0.0.3.dist-info/RECORD
