Metadata-Version: 2.1
Name: py-aiovk
Version: 0.0.3
Summary: Library for operating with VK API
Author: ScuroNeko
Project-URL: Homepage, https://github.com/ScuroNeko/py-aiovk
Project-URL: Bug Tracker, https://github.com/ScuroNeko/py-aiovk/issues
Classifier: Programming Language :: Python :: 3
Classifier: License :: OSI Approved :: MIT License
Classifier: Operating System :: OS Independent
Requires-Python: >=3.7
License-File: LICENSE
